dm.py
setup.py
daemon_manager.egg-info/PKG-INFO
daemon_manager.egg-info/SOURCES.txt
daemon_manager.egg-info/dependency_links.txt
daemon_manager.egg-info/entry_points.txt
daemon_manager.egg-info/top_level.txt