Metadata-Version: 1.0
Name: daemon-manager
Version: 0.1.4rc0
Summary: Linux Daemon Manager
Home-page: https://github.com/lodevil/daemon-manager/
Author: Du Jiong/Lodevil
Author-email: londevil@gmail.com
License: BSD
Platform: UNKNOWN
